USSZmqTools/__init__.py
USSZmqTools/core.py
USSZmqTools-0.1.0.dist-info/METADATA
USSZmqTools-0.1.0.dist-info/WHEEL
USSZmqTools-0.1.0.dist-info/top_level.txt
USSZmqTools-0.1.0.dist-info/RECORD
